gzq_package/__init__.py
gzq_package/optimization.py
gzq_package/figures_of_merit/__init__.py
gzq_package/figures_of_merit/modematch.py
gzq_package/geometries/__init__.py
gzq_package/geometries/geometry.py
gzq_package/geometries/parameterized_geometry.py
gzq_package/geometries/polygon.py
gzq_package/geometries/topology.py
gzq_package/lumerical_methods/__init__.py
gzq_package/lumerical_methods/lumerical_scripts.py
gzq_package/optimizers/__init__.py
gzq_package/optimizers/adaptive_gradient_descent.py
gzq_package/optimizers/fixed_step_gradient_descent.py
gzq_package/optimizers/generic_optimizers.py
gzq_package/optimizers/maximizer.py
gzq_package/optimizers/minimizer.py
gzq_package/optimizers/optimizer.py
gzq_package/optimizers/scipy_basin_hopping.py
gzq_package/utilities/__init__.py
gzq_package/utilities/base_script.py
gzq_package/utilities/edge.py
gzq_package/utilities/fields.py
gzq_package/utilities/gradients.py
gzq_package/utilities/load_lumerical_scripts.py
gzq_package/utilities/materials.py
gzq_package/utilities/plotter.py
gzq_package/utilities/scipy_wrappers.py
gzq_package/utilities/simulation.py
gzq_package/utilities/wavelengths.py
gzq_package-1.0.0.dist-info/LICENSE
gzq_package-1.0.0.dist-info/WHEEL
gzq_package-1.0.0.dist-info/METADATA
gzq_package-1.0.0.dist-info/RECORD
