Metadata-Version: 2.3
Name: gzq_package
Version: 1.0.0
Summary: gzq_package 是一个用于LUMERICAL进行反向设计的包。
Author-email: gzq <1653119108@qq.com>
Classifier: License :: OSI Approved :: MIT License
Project-URL: Home, https://pypi.org/manage/projects/
